[
  {
    "icon": "egg",
    "title": "Friss, pasztőrözött tyúktojásléből készült tészták",
    "text": "A frissesség és a minőség garanciája, kizárólag hazai alapanyagokból."
  },
  {
    "icon": "device_thermostat",
    "title": "Magas hőmérsékletű szárítórendszer",
    "text": "Korszerű technológia a maximális biztonság és az állandó minőség érdekében."
  },
  {
    "icon": "done_all",
    "title": "Minőségellenőrzött termékek",
    "text": "Folyamatos minőség-ellenőrzés akkreditált laboratóriumi körülmények között."
  },
  {
    "icon": "globe_location_pin",
    "title": "Hazai alapanyagokból készült házias jellegű tészták",
    "text": "Hazai alapanyagokból készült, hagyományos ízeket idéző száraztészták."
  },
  {
    "icon": "handshake",
    "title": "Kiváló partnerkapcsolatok",
    "text": "Hosszú távú, korrekt együttműködés ügyfeleinkkel és szállítóinkkal."
  }
]
